taskhub/__init__.py
taskhub/connector.py
taskhub/hub.py
taskhub/log.py
taskhub/server.py
taskhub-0.7.3.dist-info/METADATA
taskhub-0.7.3.dist-info/WHEEL
taskhub-0.7.3.dist-info/top_level.txt
taskhub-0.7.3.dist-info/RECORD
